certbot_dnshub/__init__.py
certbot_dnshub/dnshub.py
certbot_dnshub/error.py
certbot_dnshub-0.1.2.dist-info/LICENSE
certbot_dnshub-0.1.2.dist-info/METADATA
certbot_dnshub-0.1.2.dist-info/WHEEL
certbot_dnshub-0.1.2.dist-info/entry_points.txt
certbot_dnshub-0.1.2.dist-info/top_level.txt
certbot_dnshub-0.1.2.dist-info/RECORD
