Metadata-Version: 2.1
Name: certbot-dnshub
Version: 0.1.2
Summary: Multi dns provider authentication plugin for certbot
Home-page: https://github.com/warjiang/certbot-dnshub
Author: warjiang
Author-email: 1096409085@qq.com
License: Apache License 2.0
Classifier: Development Status :: 3 - Alpha
Classifier: Environment :: Plugins
Classifier: Intended Audience :: System Administrators
Classifier: License :: OSI Approved :: Apache Software License
Classifier: Operating System :: POSIX :: Linux
Classifier: Programming Language :: Python
Classifier: Programming Language :: Python :: 3
Classifier: Topic :: Internet :: WWW/HTTP
Classifier: Topic :: Security
Classifier: Topic :: System :: Installation/Setup
Classifier: Topic :: System :: Networking
Classifier: Topic :: System :: Systems Administration
Classifier: Topic :: Utilities
Requires-Python: >=3.0
License-File: LICENSE
Requires-Dist: acme >=0.21.1
Requires-Dist: certbot >=0.21.1
Requires-Dist: dns-lexicon
Requires-Dist: mock
Requires-Dist: setuptools
Requires-Dist: zope.interface
